eurocropsml/__init__.py
eurocropsml/cli.py
eurocropsml/settings.py
eurocropsml/utils.py
eurocropsml/acquisition/__init__.py
eurocropsml/acquisition/builder.py
eurocropsml/acquisition/cli.py
eurocropsml/acquisition/collector.py
eurocropsml/acquisition/config.py
eurocropsml/acquisition/copier.py
eurocropsml/acquisition/region.py
eurocropsml/acquisition/utils.py
eurocropsml/acquisition/clipping/__init__.py
eurocropsml/acquisition/clipping/clipper.py
eurocropsml/acquisition/clipping/utils.py
eurocropsml/configs/__init__.py
eurocropsml/configs/acquisition/__init__.py
eurocropsml/configs/acquisition/config.yaml
eurocropsml/configs/acquisition/cfg/__init__.py
eurocropsml/configs/acquisition/cfg/austria.yaml
eurocropsml/configs/acquisition/cfg/estonia.yaml
eurocropsml/configs/acquisition/cfg/latvia.yaml
eurocropsml/configs/acquisition/cfg/portugal.yaml
eurocropsml/configs/dataset/__init__.py
eurocropsml/configs/dataset/config.yaml
eurocropsml/configs/dataset/preprocess/__init__.py
eurocropsml/configs/dataset/preprocess/default.yaml
eurocropsml/configs/dataset/split/__init__.py
eurocropsml/configs/dataset/split/default.yaml
eurocropsml/configs/dataset/split/overlap_latvia.yaml
eurocropsml/configs/dataset/split/overlap_portugal.yaml
eurocropsml/configs/dataset/split/portugal.yaml
eurocropsml/dataset/__init__.py
eurocropsml/dataset/base.py
eurocropsml/dataset/cli.py
eurocropsml/dataset/config.py
eurocropsml/dataset/dataset.py
eurocropsml/dataset/download.py
eurocropsml/dataset/preprocess.py
eurocropsml/dataset/splits.py
eurocropsml/dataset/utils.py
eurocropsml-0.4.1.dist-info/METADATA
eurocropsml-0.4.1.dist-info/WHEEL
eurocropsml-0.4.1.dist-info/entry_points.txt
eurocropsml-0.4.1.dist-info/licenses/LICENSE
eurocropsml-0.4.1.dist-info/RECORD
