Metadata-Version: 2.4
Name: eurocropsml
Version: 0.4.1
Summary: EuroCropsML is a ready-to-use benchmark dataset for few-shot crop type classification using Sentinel-2 imagery.
Project-URL: Documentation, https://eurocropsml.readthedocs.io/en/latest/
Project-URL: Changelog, https://github.com/dida-do/eurocropsml/blob/main/CHANGELOG.md
Project-URL: GitHub, https://github.com/dida-do/eurocropsml
Author-email: Joana Reuss <joana.reuss@tum.de>, Jan Macdonald <jan.macdonald@dida.do>
Maintainer-email: Joana Reuss <joana.reuss@tum.de>, Jan Macdonald <jan.macdonald@dida.do>
License-Expression: MIT
License-File: LICENSE
Classifier: License :: OSI Approved :: MIT License
Classifier: Operating System :: OS Independent
Classifier: Programming Language :: Python :: 3
Classifier: Typing :: Typed
Requires-Python: >=3.10
Requires-Dist: bs4
Requires-Dist: geopandas
Requires-Dist: hydra-core
Requires-Dist: mmap-ninja
Requires-Dist: numpy
Requires-Dist: pyarrow
Requires-Dist: pydantic
Requires-Dist: pydantic-settings
Requires-Dist: pyogrio
Requires-Dist: rasterio
Requires-Dist: requests
Requires-Dist: scikit-learn
Requires-Dist: selenium
Requires-Dist: torch>=2.0
Requires-Dist: typer[all]
Requires-Dist: types-requests
Requires-Dist: webdriver-manager
Requires-Dist: xmlschema
Provides-Extra: dev
Requires-Dist: black; extra == 'dev'
Requires-Dist: coverage[toml]>=5.3; extra == 'dev'
Requires-Dist: darglint; extra == 'dev'
Requires-Dist: furo>=2024.05.06; extra == 'dev'
Requires-Dist: isort; extra == 'dev'
Requires-Dist: mypy; extra == 'dev'
Requires-Dist: myst-parser; extra == 'dev'
Requires-Dist: pep8-naming; extra == 'dev'
Requires-Dist: pytest; extra == 'dev'
Requires-Dist: pytest-mock; extra == 'dev'
Requires-Dist: pytest-xdist; extra == 'dev'
Requires-Dist: ruff>=0.4.8; extra == 'dev'
Requires-Dist: sphinx; extra == 'dev'
Requires-Dist: sphinx-copybutton; extra == 'dev'
Requires-Dist: sphinx-design; extra == 'dev'
Requires-Dist: sphinx-tippy; extra == 'dev'
Requires-Dist: sphinxcontrib-mermaid; extra == 'dev'
Requires-Dist: torch==2.2.0; extra == 'dev'
Requires-Dist: tox; extra == 'dev'
Requires-Dist: tox-ignore-env-name-mismatch; extra == 'dev'
Requires-Dist: typer-cli; extra == 'dev'
Provides-Extra: docs
Requires-Dist: furo>=2024.05.06; extra == 'docs'
Requires-Dist: myst-parser; extra == 'docs'
Requires-Dist: sphinx; extra == 'docs'
Requires-Dist: sphinx-copybutton; extra == 'docs'
Requires-Dist: sphinx-design; extra == 'docs'
Requires-Dist: sphinx-tippy; extra == 'docs'
Requires-Dist: sphinxcontrib-mermaid; extra == 'docs'
Requires-Dist: typer-cli; extra == 'docs'
Provides-Extra: tests
Requires-Dist: black; extra == 'tests'
Requires-Dist: coverage[toml]>=5.3; extra == 'tests'
Requires-Dist: darglint; extra == 'tests'
Requires-Dist: isort; extra == 'tests'
Requires-Dist: mypy; extra == 'tests'
Requires-Dist: pep8-naming; extra == 'tests'
Requires-Dist: pytest; extra == 'tests'
Requires-Dist: pytest-mock; extra == 'tests'
Requires-Dist: pytest-xdist; extra == 'tests'
Requires-Dist: ruff>=0.4.8; extra == 'tests'
